enchantress/__init__.py
enchantress-0.0.1.dist-info/LICENSE.txt
enchantress-0.0.1.dist-info/METADATA
enchantress-0.0.1.dist-info/WHEEL
enchantress-0.0.1.dist-info/top_level.txt
enchantress-0.0.1.dist-info/RECORD
